scicat_sdk_pydantic/__init__.py
scicat_sdk_pydantic/api_client.py
scicat_sdk_pydantic/api_response.py
scicat_sdk_pydantic/configuration.py
scicat_sdk_pydantic/exceptions.py
scicat_sdk_pydantic/py.typed
scicat_sdk_pydantic/rest.py
scicat_sdk_pydantic/api/__init__.py
scicat_sdk_pydantic/api/admin_api.py
scicat_sdk_pydantic/api/auth_api.py
scicat_sdk_pydantic/api/datasets_api.py
scicat_sdk_pydantic/api/default_api.py
scicat_sdk_pydantic/api/elastic_search_api.py
scicat_sdk_pydantic/api/instruments_api.py
scicat_sdk_pydantic/api/jobs_api.py
scicat_sdk_pydantic/api/logbooks_api.py
scicat_sdk_pydantic/api/origdatablocks_api.py
scicat_sdk_pydantic/api/policies_api.py
scicat_sdk_pydantic/api/proposals_api.py
scicat_sdk_pydantic/api/published_data_api.py
scicat_sdk_pydantic/api/samples_api.py
scicat_sdk_pydantic/api/user_identities_api.py
scicat_sdk_pydantic/api/users_api.py
scicat_sdk_pydantic/models/__init__.py
scicat_sdk_pydantic/models/attachment.py
scicat_sdk_pydantic/models/count_api_response.py
scicat_sdk_pydantic/models/create_attachment_dto.py
scicat_sdk_pydantic/models/create_custom_jwt.py
scicat_sdk_pydantic/models/create_dataset_datablock_dto.py
scicat_sdk_pydantic/models/create_dataset_dto.py
scicat_sdk_pydantic/models/create_dataset_orig_datablock_dto.py
scicat_sdk_pydantic/models/create_derived_dataset_obsolete_dto.py
scicat_sdk_pydantic/models/create_instrument_dto.py
scicat_sdk_pydantic/models/create_job_dto.py
scicat_sdk_pydantic/models/create_measurement_period_dto.py
scicat_sdk_pydantic/models/create_orig_datablock_dto.py
scicat_sdk_pydantic/models/create_policy_dto.py
scicat_sdk_pydantic/models/create_proposal_dto.py
scicat_sdk_pydantic/models/create_published_data_dto.py
scicat_sdk_pydantic/models/create_raw_dataset_obsolete_dto.py
scicat_sdk_pydantic/models/create_sample_dto.py
scicat_sdk_pydantic/models/create_sub_attachment_dto.py
scicat_sdk_pydantic/models/create_user_jwt.py
scicat_sdk_pydantic/models/create_user_settings_dto.py
scicat_sdk_pydantic-4.9.0.dist-info/METADATA
scicat_sdk_pydantic-4.9.0.dist-info/WHEEL
scicat_sdk_pydantic-4.9.0.dist-info/top_level.txt
scicat_sdk_pydantic-4.9.0.dist-info/RECORD
